setup.py
pygmatrix/__init__.py
pygmatrix.egg-info/PKG-INFO
pygmatrix.egg-info/SOURCES.txt
pygmatrix.egg-info/dependency_links.txt
pygmatrix.egg-info/requires.txt
pygmatrix.egg-info/top_level.txt