Metadata-Version: 1.1
Name: pygmatrix
Version: 0.1
Summary: PyGMatrix
Home-page: https://github.com/spothero/pygmatrix
Author: SpotHero
Author-email: cezar@spothero.com
License: UNKNOWN
Download-URL: https://github.com/spothero/pygmatrix/tarball/0.1
Platform: UNKNOWN
